setup.cfg
setup.py
geohasher/__init__.py
geohasher/hasher.py
geohasher.egg-info/PKG-INFO
geohasher.egg-info/SOURCES.txt
geohasher.egg-info/dependency_links.txt
geohasher.egg-info/entry_points.txt
geohasher.egg-info/not-zip-safe
geohasher.egg-info/paster_plugins.txt
geohasher.egg-info/top_level.txt
