Metadata-Version: 1.0
Name: geohasher
Version: 0.1dev
Summary: Geohash without the iteration
Home-page: http://dingoskidneys.com/
Author: Daniel Holth
Author-email: dholth@fastmail.fm
License: MIT
Keywords: geohash
Platform: UNKNOWN
